{
  "elements": [
    {
      "content": {
        "json": {
          "children": [
            {
              "type": "class",
              "children": [
                {
                  "type": "paragraph",
                  "children": [
                    {
                      "text": "Sed deserunt reiciendis aut culpa voluptatem et voluptas quae est incidunt ratione! Rem sint expedita qui dolores doloribus "
                    },
                    {
                      "type": "embed",
                      "nodeId": "cle0l041n7v3i09mzdr8xhewf",
                      "children": [
                        {
                          "text": ""
                        }
                      ],
                      "isInline": true,
                      "nodeType": "Variable"
                    },
                    {
                      "text": " est natus corrupti sit "
                    },
                    {
                      "type": "embed",
                      "nodeId": "cle3h3p0ejvn00amulhuy3mpr",
                      "children": [
                        {
                          "text": ""
                        }
                      ],
                      "isInline": true,
                      "nodeType": "Variable"
                    },
                    {
                      "text": " rerum dolores 33 assumenda corrupti sed nemo omnis."
                    }
                  ]
                }
              ],
              "className": "repeat"
            },
            {
              "type": "paragraph",
              "children": [
                {
                  "text": "Est voluptatem galisum 33 recusandae esse et mollitia recusandae aut adipisci voluptas? Ut quia delectus qui debitis itaque et ipsa recusandae. Non necessitatibus optio sit praesentium laudantium eum soluta voluptatibus sed internos temporibus quo impedit quaerat ex officia reiciendis non velit officiis?"
                }
              ]
            }
          ]
        },
        "references": [
          {
            "id": "cle0l041n7v3i09mzdr8xhewf",
            "name": "F: First Name",
            "apiReference": "firstName",
            "type": "first"
          },
          {
            "id": "cle3h3p0ejvn00amulhuy3mpr",
            "name": "O: First Name",
            "apiReference": "firstName",
            "type": "other"
          }
        ]
      },
      "id": "cledfevp2csyx0bn48btr8z5h",
      "name": "Quis id provident",
      "type": "doloremque_voluptas"
    },
    {
      "content": {
        "json": {
          "children": [
            {
              "type": "paragraph",
              "children": [
                {
                  "text": "Lorem ipsum dolor sit amet. Aut possimus itaque non accusantium laudantium vel rerum rerum ea voluptatem perferendis vel voluptas expedita et error magni eum iste enim. Sed exercitationem earum aut nesciunt voluptatem qui asperiores adipisci. Et aperiam nobis qui ratione esse vel aliquid cumque qui sint sunt aut aspernatur dolore aut itaque voluptas et odit possimus. Et voluptatem enim ut delectus autem sed consequatur totam ea harum autem. Vel reprehenderit voluptatibus aut quia repellendus ut quos similique est beatae dolor in aliquid vitae."
                }
              ]
            },
            {
              "type": "class",
              "children": [
                {
                  "type": "paragraph",
                  "children": [
                    {
                      "text": "In tempore iure et praesentium voluptatibus aut voluptatibus accusamus sit ipsum corporis est consequatur ipsam. Aut nisi "
                    },
                    {
                      "type": "embed",
                      "nodeId": "cle0l041n7v3i09mzdr8xhewf",
                      "children": [
                        {
                          "text": ""
                        }
                      ],
                      "isInline": true,
                      "nodeType": "Variable"
                    },
                    {
                      "text": " "
                    },
                    {
                      "type": "embed",
                      "nodeId": "cle0l0agt7v6a09mzlst8vb74",
                      "children": [
                        {
                          "text": ""
                        }
                      ],
                      "isInline": true,
                      "nodeType": "Variable"
                    },
                    {
                      "text": " exercitationem ex quos "
                    },
                    {
                      "type": "embed",
                      "nodeId": "cle0l2bhu7sso09n33nuz8gu5",
                      "children": [
                        {
                          "text": ""
                        }
                      ],
                      "isInline": true,
                      "nodeType": "Variable"
                    },
                    {
                      "text": " necessitatibus qui similique voluptas qui officiis nostrum "
                    },
                    {
                      "type": "embed",
                      "nodeId": "cle3hcs38keti0amu1oc169d9",
                      "children": [
                        {
                          "text": ""
                        }
                      ],
                      "isInline": true,
                      "nodeType": "Variable"
                    },
                    {
                      "text": " aut quibusdam dicta At omnis repellat non tenetur quia. Et eligendi totam ea quidem quae nam voluptate voluptatum."
                    }
                  ]
                }
              ],
              "className": "repeat"
            },
            {
              "type": "paragraph",
              "children": [
                {
                  "text": "Et nihil numquam et autem blanditiis eum tempore autem est quae quam id itaque possimus vel deleniti dolorem. In eveniet quasi a excepturi iure aut dolorem voluptas a quibusdam suscipit. Et ipsam deserunt sed autem accusantium sit unde debitis aut quia harum et dolores omnis. Qui quasi quia vel porro sint sed repudiandae tenetur et minus placeat in natus dolorem non praesentium voluptatem. "
                },
                {
                  "type": "embed",
                  "nodeId": "cle3her62kn0o0amxzuztw6qp",
                  "children": [
                    {
                      "text": ""
                    }
                  ],
                  "isInline": true,
                  "nodeType": "Variable"
                },
                {
                  "text": " ed cumque laudantium sit unde illo et mollitia aspernatur eos enim maiores non dolor natus rem nemo labore qui sequi cupiditate. Et modi omnis qui quos veniam sit reprehenderit consequatur non veritatis sequi."
                }
              ]
            },
            {
              "type": "paragraph",
              "children": [
                {
                  "text": "In officiis consequuntur aut incidunt dicta non molestiae illo est nihil aperiam. Qui natus natus quo voluptas velit sed consequatur quia. Sed enim amet sed iste quia est sunt dignissimos ut possimus rerum et provident sapiente qui sint sunt in velit voluptatem. Qui quod voluptatum non illo reiciendis hic placeat perferendis? Ea nobis consequatur rem quam molestias rem delectus velit qui neque reprehenderit non voluptate dolores eos sint recusandae."
                }
              ]
            }
          ]
        },
        "references": [
          {
            "id": "cle0l041n7v3i09mzdr8xhewf",
            "name": "F: First Name",
            "apiReference": "firstName",
            "type": "first"
          },
          {
            "id": "cle0l0agt7v6a09mzlst8vb74",
            "name": "F: Last Name",
            "apiReference": "lastName",
            "type": "first"
          },
          {
            "id": "cle0l2bhu7sso09n33nuz8gu5",
            "name": "F: Possessive Adjective",
            "apiReference": "possessiveAdjective",
            "type": "first"
          },
          {
            "id": "cle3hcs38keti0amu1oc169d9",
            "name": "O: Possessive Adjective",
            "apiReference": "possessiveAdjective",
            "type": "other"
          },
          {
            "id": "cle3her62kn0o0amxzuztw6qp",
            "name": "Name",
            "apiReference": "name",
            "type": "ceremony"
          }
        ]
      },
      "id": "cledf78fclkpc0bn5erae23rg",
      "name": "Ut vitae dolorem ut quia quibusdam",
      "type": "eos_magnam_placeat"
    },
    {
      "content": {
        "json": {
          "children": [
            {
              "type": "paragraph",
              "children": [
                {
                  "text": "Qui recusandae maxime sed aliquam provident qui dolor eveniet eos aperiam temporibus vel eaque voluptas et quas rerum. Et autem suscipit ea iusto quos id tenetur libero ea nostrum voluptatem? Cum expedita dolor est mollitia corrupti et neque maxime ea internos internos aut galisum facere At tenetur possimus? Et nulla officia ut inventore rerum ut quisquam dolore sit incidunt officiis sit voluptatum assumenda. Nam galisum animi et consequatur atque sit aperiam temporibus sit vero sint id sunt magni. Vel iusto consequatur qui earum fuga non iure corrupti ut deserunt delectus? Rem suscipit odit ut odit deserunt rem galisum doloremque in nemo nesciunt hic dignissimos dolorum vel sapiente repudiandae in sint mollitia."
                }
              ]
            },
            {
              "type": "paragraph",
              "children": [
                {
                  "text": "Qui voluptas perferendis id Quis dolor ad deserunt architecto et officia minus et expedita internos aut quasi rerum eos accusamus nesciunt! In fugit voluptas qui repudiandae architecto qui optio tenetur. Non provident tempora ea repellat exercitationem sed voluptas quasi non exercitationem natus sit aspernatur illum ab repellat tempore aut repudiandae voluptatem! Eum rerum laboriosam ut atque obcaecati et facilis nostrum ad odit iure sit maiores consequatur sed quia accusantium. In nostrum omnis qui velit necessitatibus nam itaque voluptate."
                }
              ]
            },
            {
              "type": "paragraph",
              "children": [
                {
                  "text": "Ut nulla adipisci ad quas reprehenderit est cupiditate eligendi est tempore explicabo aut quae voluptas. Ut velit explicabo aut provident quis eum neque ipsum quo modi dolores aut galisum facilis qui nisi dolor est vero assumenda. Sit incidunt laborum in odio omnis et enim consequuntur. Ut nesciunt eligendi sed voluptates omnis ut iure ullam ut assumenda doloremque ut voluptas excepturi. Sit obcaecati quos id autem voluptatem vel architecto excepturi. Et iusto sunt hic reiciendis dolore et aspernatur sunt est inventore earum sed dicta fuga ea cumque blanditiis. Eum magnam omnis sit aliquid saepe ea molestiae iste non earum repudiandae qui alias ipsam."
                }
              ]
            },
            {
              "type": "paragraph",
              "children": [
                {
                  "text": "Ut facere modi quo voluptatem officiis ut quia labore qui alias illum est consequuntur corporis in asperiores culpa qui accusantium veniam. Vel cumque reprehenderit id Quis nobis vel fugit saepe. Sit enim soluta vel galisum facilis eum modi veritatis ut dolores nostrum qui quam delectus. Hic nihil quia ut soluta internos vel quibusdam recusandae. Nam ratione voluptatum sed blanditiis neque aut dolorem provident est accusantium perspiciatis est dolor voluptatem in error sunt."
                }
              ]
            }
          ]
        },
        "references": []
      },
      "id": "cledgqdhemhe40blrhl4y4mii",
      "name": "Officiis recusandae",
      "type": "omnis_veniam"
    },
    {
      "content": {
        "json": {
          "children": [
            {
              "type": "paragraph",
              "children": [
                {
                  "text": "Aut consequatur error ad recusandae ullam hic quaerat quae id facere delectus. Qui nihil ducimus 33 dignissimos dolorum aut mollitia reiciendis. Eos earum quod qui autem sint ex perferendis recusandae est quia maxime aut odio reiciendis est repellat quam aut rerum omnis. Sit alias ratione ut quam quibusdam sed voluptatibus quia non nihil quia et quam quia. In dolor consectetur est minima autem et dolorum sequi et nihil libero et laboriosam quis a sint quia ea illo Quis! Qui officia quod aut quidem rerum qui dolorem vitae et rerum cupiditate eos consectetur officia. Eum minus aliquam ad maiores quia eos alias temporibus et ullam eaque. Qui maiores earum et molestias nulla ab autem voluptates non dolorum maxime in explicabo repudiandae eos dolor amet sed voluptatem fuga. Eos repellendus recusandae sit facilis nesciunt aut praesentium quis."
                }
              ]
            },
            {
              "type": "paragraph",
              "children": [
                {
                  "text": "Aut odit laborum ex molestiae alias et numquam iure aut possimus molestiae sit quia distinctio eum expedita aliquid ea quis exercitationem. Non quas eaque et commodi quia eum assumenda aliquam? Non impedit fuga aut natus numquam et magni sint non alias totam ut quibusdam libero in voluptatem molestiae! Ad aliquid fuga vel fugit nesciunt et soluta earum et inventore eius. Et nihil nostrum sit illo praesentium eos tempore debitis At voluptates nulla."
                }
              ]
            },
            {
              "type": "paragraph",
              "children": [
                {
                  "text": "Et consectetur facere et repellendus voluptatem et exercitationem voluptatem et nisi saepe sit tenetur cumque. Et numquam nihil non quia galisum sed obcaecati aperiam quo sapiente maxime aut velit voluptatem! Ut distinctio rerum qui voluptatem modi id quidem beatae? Sit provident inventore et molestiae eius et saepe dignissimos. Et voluptatem iste ad laborum omnis in obcaecati quidem. Ut quidem velit in sunt repudiandae At nemo amet ad debitis quod non repellendus laudantium quo quibusdam voluptates. Eum repellendus rerum nam adipisci quos vel ratione corrupti aut odio molestias. Cum adipisci aperiam qui voluptatem quia et dolores illo et itaque repellendus et laboriosam aliquid ut autem quam. Ex perspiciatis odit et beatae nesciunt non quam laborum est totam libero non repellendus consequatur ut animi nostrum."
                }
              ]
            },
            {
              "type": "paragraph",
              "children": [
                {
                  "text": "Eum explicabo esse ut magnam velit aut veritatis rerum et laudantium recusandae quo fuga exercitationem. Aut sunt reprehenderit non omnis quaerat aut earum omnis hic minima eligendi eum sint aspernatur aut quae beatae sit iste quasi. Est tempore impedit qui voluptatem veniam eos ipsa dignissimos ut magni nemo in reprehenderit nobis vel molestias quasi et iusto eius. Et galisum amet nam nisi fugit nam quasi quas et nihil error a assumenda totam qui beatae illo. Aut eius voluptate quo ipsam aperiam est mollitia nihil et voluptate fugiat ad aperiam saepe ad quia dolores aut corrupti voluptatem. Est modi vero At autem necessitatibus aut iste explicabo non quae odio. Vel veniam dolor in maiores fugiat est ullam rerum vel odio dolorem ex eligendi nihil ab odio Quis."
                }
              ]
            },
            {
              "type": "paragraph",
              "children": [
                {
                  "text": "Sed tempore perspiciatis vel ipsam iste sed doloremque voluptas est sequi laboriosam et autem quia. Et sint eveniet est praesentium nesciunt qui repellat ratione aut aliquid sint et dolorem saepe est quidem nobis et rerum dolorem? Ab tempora dicta quo doloremque ipsa eos tenetur autem et asperiores excepturi eos soluta eaque. Eum aperiam fuga sed atque expedita nam galisum quia non consequuntur ipsa eos doloribus alias nam soluta amet et dicta velit. Qui earum omnis et Quis modi ut sequi repellendus."
                }
              ]
            }
          ]
        },
        "references": []
      },
      "id": "cledgrodomhyv0blrqtut4t0a",
      "name": "Repellendus blanditiis",
      "type": "eaque_ut_minus"
    }
  ],
  "id": "cledhd7nvmykt0bn58z8scyxu",
  "length": "longer",
  "name": "Sit galisum distinctio",
  "style": [
    "fringilla",
    "libero",
    "lobortis"
  ]
}
